README.rst
setup.py
deproulette/__init__.py
deproulette.egg-info/PKG-INFO
deproulette.egg-info/SOURCES.txt
deproulette.egg-info/dependency_links.txt
deproulette.egg-info/top_level.txt