Metadata-Version: 1.0
Name: deproulette
Version: 1.1
Summary: You never know what you get. Such is life.
Home-page: https://github.com/joar/deproulette
Author: Joar Wandborg
Author-email: name \x40 lastname. se
License: UNKNOWN
Platform: UNKNOWN
